{
  "UsernamePassword" : {
    "@type" : "UsernamePassword",
    "password" : "I am a short string.",
    "username" : "I am a short string.",
    "PasswordHint" : [ {
      "value" : null,
      "answer" : "I am a short string.",
      "question" : "I am a short string."
    }, {
      "value" : null,
      "answer" : "I am a short string.",
      "question" : "I am a short string."
    }, {
      "value" : null,
      "answer" : "I am a short string.",
      "question" : "I am a short string."
    } ]
  }
}